AUTHORS
COPYING
LICENSE
MANIFEST.in
README
setup.cfg
setup.py
docs/Makefile
docs/echo.py.txt
docs/eclipse_cdt_style.xml
docs/make.bat
docs/source/api.rst
docs/source/conf.py
docs/source/global.rst.inc
docs/source/hacking.rst
docs/source/index.rst
docs/source/installation.rst
docs/source/quickstart.rst
docs/source/examples/logger.py
docs/source/examples/patterns.py
docs/source/examples/simple.py
docs/source/examples/tricks.json
docs/source/examples/tricks.yaml
src/_watchdog_fsevents.c
src/_watchdog_fsevents.h
src/_watchdog_util.c
src/watchdog_fsevents.c
src/infi.watchdog.egg-info/PKG-INFO
src/infi.watchdog.egg-info/SOURCES.txt
src/infi.watchdog.egg-info/dependency_links.txt
src/infi.watchdog.egg-info/entry_points.txt
src/infi.watchdog.egg-info/not-zip-safe
src/infi.watchdog.egg-info/requires.txt
src/infi.watchdog.egg-info/top_level.txt
src/watchdog/__init__.py
src/watchdog/events.py
src/watchdog/version.py
src/watchdog/watchmedo.py
src/watchdog/observers/__init__.py
src/watchdog/observers/api.py
src/watchdog/observers/fsevents.py
src/watchdog/observers/inotify.py
src/watchdog/observers/kqueue.py
src/watchdog/observers/polling.py
src/watchdog/observers/read_directory_changes.py
src/watchdog/observers/read_directory_changes_async.py
src/watchdog/observers/winapi.py
src/watchdog/observers/winapi_common.py
src/watchdog/tricks/__init__.py
src/watchdog/utils/__init__.py
src/watchdog/utils/bricks.py
src/watchdog/utils/decorators.py
src/watchdog/utils/dirsnapshot.py
src/watchdog/utils/echo.py
src/watchdog/utils/platform.py